django_stubs_ext/__init__.py
django_stubs_ext/aliases.py
django_stubs_ext/annotations.py
django_stubs_ext/patch.py
django_stubs_ext/py.typed
django_stubs_ext/settings.py
django_stubs_ext/types.py
django_stubs_ext/db/__init__.py
django_stubs_ext/db/router.py
django_stubs_ext/db/models/__init__.py
django_stubs_ext/db/models/manager.py
django_stubs_ext-5.2.4.dist-info/METADATA
django_stubs_ext-5.2.4.dist-info/WHEEL
django_stubs_ext-5.2.4.dist-info/licenses/LICENSE.md
django_stubs_ext-5.2.4.dist-info/RECORD
